CHANGES.txt
LICENSE.txt
MANIFEST.in
README.txt
setup.py
InsightsOnCode.egg-info/PKG-INFO
InsightsOnCode.egg-info/SOURCES.txt
InsightsOnCode.egg-info/dependency_links.txt
InsightsOnCode.egg-info/requires.txt
InsightsOnCode.egg-info/top_level.txt
bin/sample_easy.py
docs/docs.txt
insightsoncode/__init__.py
insightsoncode/ioc_wrappers.py
insightsoncode/constants/__init__.py
insightsoncode/constants/constants.py
insightsoncode/constants/wrapperdictconstants.py
insightsoncode/constants/wrapperlistconstants.py
insightsoncode/constants/wrapperstringconstants.py
insightsoncode/helpers/__init__.py
insightsoncode/helpers/helpers.py
insightsoncode/helpers/http_helpers.py
insightsoncode/helpers/stack_helpers.py