Metadata-Version: 2.1
Name: InsightsOnCode
Version: 0.1.1.6
Summary: UNKNOWN
Home-page: http://pypi.python.org/pypi/InsightsOnCode/
Author: Siddhanth Ramani
Author-email: dhanth20@gmail.com
License: LICENSE.txt
Platform: UNKNOWN
License-File: LICENSE.txt
